[
  {
    "event_title": "Endgame: Duchamp, chess and the avant-garde",
    "event_start": "29/10/2016",
    "event_end": "22/01/2017",
    "event_image-src": "http://www.fmirobcn.org/media/upload/gif/cache/sonia_delaunay_1472816255_255.jpg",
    "event_text": "Endgame. Duchamp, chess and the avant-garde is an account of twentieth-century avant-garde movements up to the beginning of conceptual art, told from the angle of what appears to be a minor anecdote: the game of chess.",
    "event_link": "about  \"Endgame: Duchamp, chess and the avant-garde\"",
    "event_link-href": "http://www.fmirobcn.org/exhibitions/5708/endgame-duchamp-chess-and-the-avant-garde",
    "event_id": "/exhibitions/5708/endgame-duchamp-chess-and-the-avant-garde",
    "event_maplink__1": "null",
    "event_organizer__Fundación Joan Miró": "null",
    "event_venue__Fundación Joan Miró": "null",
    "event_cost__7": "null",
    "event_category__Exhibition__Fundación Joan Miró": "null"
  }
]