[
  {
    "event_link": "http://www.fundaciotapies.org/site/spip.php?article8473",
    "event_title": "Documentos de acción. Obras de las colecciones Denney y Cordier (1947-1965)",
    "event_description": "<p><img src='http://www.fundaciotapies.org/site/IMG/arton8473.gif' width='228' height='182' alt='Documentos de acción. Obras de las colecciones Denney y Cordier (1947-1965)' />..........................................................................................................................</p><p><a href='http://www.fundaciotapies.org/site/spip.php?article8473' target='_blank'>+info</a></p>",
    "event_start": "01/28/2016",
    "event_end": "05/22/2016",
    "event_category": "Exposición, Fundación Antoni Tàpies",
    "event_organizer": "Fundación Antoni Tàpies",
    "event_venue": "Fundación Antoni Tàpies",
    "event_cost": "7",
    "event_map": 1,
    "event_maplink": 1,
    "event_allday": 1,
    "event_start-time": "",
    "event_end-time": ""
  },
  {
    "event_link": "http://www.fundaciotapies.org/site/spip.php?article8477",
    "event_title": "Antoni Tàpies. Colección, 1955–65",
    "event_description": "<p><img src='http://www.fundaciotapies.org/site/IMG/arton8477.jpg' width='228' height='182' alt='Antoni Tàpies. Colección, 1955–65' />..........................................................................................................................</p><p><a href='http://www.fundaciotapies.org/site/spip.php?article8477' target='_blank'>+info</a></p>",
    "event_start": "01/19/2016",
    "event_end": "05/22/2016",
    "event_category": "Exposición, Fundación Antoni Tàpies",
    "event_organizer": "Fundación Antoni Tàpies",
    "event_venue": "Fundación Antoni Tàpies",
    "event_cost": "7",
    "event_map": 1,
    "event_maplink": 1,
    "event_allday": 1,
    "event_start-time": "",
    "event_end-time": ""
  }
]
