[{"EVENT NAME":"Alvaro Sánchez-Montañés                         - No como el caos","VENUE NAME":"Museo Can Framis","ORGANIZER NAME":"Museo Can Framis","START DATE":"10/01/2018","START TIME":"","END DATE":"01/20/2018","END TIME":"","ALL DAY EVENT?":1,"CATEGORIES":"Exposición, Museo Can Framis, Pintura, Arte local, Próximas inauguraciones","EVENT COST":"5","EVENT WEBSITE":"http://www.fundaciovilacasas.com/es/exposicion/no-como-el-caos","SHOW MAP LINK?":1,"SHOW MAP?":1,"EVENT DESCRIPTION":"<p><img src='http://gestio.fundaciovilacasas.com/contactes//upfiles/exposicions/imatges/th_th_A16814834.jpg' width='228' height='182' alt='Alvaro Sánchez-Montañés                         - No como el caos' /></p>","EVENT IMAGE":"https://gestio.fundaciovilacasas.com/contactes//upfiles/exposicions/imatges/th_th_A16814834.jpg"},{"EVENT NAME":"Jorge R. Pombo                         - Viaje a la esencia de la pintura","VENUE NAME":"Museo Can Framis","ORGANIZER NAME":"Museo Can Framis","START DATE":"10/01/2018","START TIME":"","END DATE":"01/20/2018","END TIME":"","ALL DAY EVENT?":1,"CATEGORIES":"Exposición, Museo Can Framis, Pintura, Arte local, Próximas inauguraciones","EVENT COST":"5","EVENT WEBSITE":"http://www.fundaciovilacasas.com/es/exposicion/viaje-a-la-esencia-de-la-pintura","SHOW MAP LINK?":1,"SHOW MAP?":1,"EVENT DESCRIPTION":"<p><img src='http://gestio.fundaciovilacasas.com/contactes//upfiles/exposicions/imatges/th_th_A18760315.jpg' width='228' height='182' alt='Jorge R. Pombo                         - Viaje a la esencia de la pintura' /></p>","EVENT IMAGE":"https://gestio.fundaciovilacasas.com/contactes//upfiles/exposicions/imatges/th_th_A18760315.jpg"}]
