[{"EVENT NAME":"Tallers Oberts BCN 18","VENUE NAME":"Fàbrica Lehmann","ORGANIZER NAME":"Fàbrica Lehmann","START DATE":"05/11/2018","START TIME":"","END DATE":"05/13/2018","END TIME":"","ALL DAY EVENT?":1,"CATEGORIES":"","EVENT COST":"","EVENT WEBSITE":"https://www.facebook.com/events/1990266517889692/","SHOW MAP LINK?":1,"SHOW MAP?":1,"EVENT DESCRIPTION":"<p><img src='http://scontent-mad1-1.xx.fbcdn.net/v/t1.0-0/s526x296/31378788_2173031986057069_2986424592089743360_n.jpg?_nc_cat=0&_nc_eui2=v1%3AAeFcJfFObXgvl-l2ztd3Bp37izMjE8gGgRTQKbQ6H6I_e7JDifzvX24dziwZ_l8Y8CSRkYhAXFKkZDPBvoqr8_PJq4XLBgBMTu-HJfuaeTp7Og&oh=7c686b7ffc75f1a26c0694545492419b&oe=5B580288' width='228' height='182' alt='Tallers Oberts BCN 18' />Una vegada més la Fàbrica Lehmann​ participa als Tallers Oberts BCN. Unes jornades de portes obertes on artistes plàstics i artesans professionals mostren la seva obra i el seu espai de treball a la ciutadania!<br /> <br /> Inscripcions obertes ✨✨<br /> <br /> - - - - -  - -<br /> <br /> TALLER DE CERÁMICA A ESPAI BLAU-COBALT<br /> \"Vine a fer un bol\" .......Primer contacte amb el fang........<br /> <br /> HORARI<br /> Divendres d' 11 a 12; de 12'30 a 13´30; 16 a 17h; 17'30 a 18'30; 20 a 21h.<br /> Dissabte d'11 a 12; de 12'30 a 13'30; 16 a 17; 17'30 a 18'30 a 19 a 20h....<br /> Diumenge d'11 a 12; de 12'30 a 13'30; 16 a 17; 17'30 a 18'30 a 19 a 20h.<br /> Preu: 15€<br /> INSCRIPCIÓ PRÈVIA / Màxim 6 alumnes. <br /> <br /> Es proposa fer una peça de ceràmica, un bol o similar. O senzillament jugar amb el fang per tenir un primer contacte amb el material.<br /> <br /> https://www.facebook.com/blaucobalt.barcelona.1<br /> INSCRIPCIONS a blaucobaltbarcelona@gmail.com o per telèfon al 678718297<br /> <br /> - - - - -  - -<br /> <br /> TALLER DE SERIGRAFIA A DINAMO-STUDIO<br /> <br /> Dia: dissabte 12 de maig<br /> Horari: d'11 a 12:30h.<br /> Preu: 25 € (inclou tots els materials)<br /> INSCRIPCIÓ PRÈVIA / Màxim 10 alumnes. <br /> <br /> Barregem la tècnica de l'estergit i la serigrafia per crear divertides tote bags al més pur estil d'Andy Warhol. Explicarem tot el procediment serigràfic pas a pas des de zero patatero i tindrem diferents personatges populars per triar i colors per a estampar al nostre gust;)<br /> Totebag inclosa de REGAL!<br /> <br /> http://www.dinamo-studio.com/agenda/tote-pop-bag-serigrafia-stencil/<br /> <br /> - - - - -  - -<br /> <br /> TALLER DE SEGELLS A DINAMO-STUDIO<br /> <br /> Dia: diumenge 13 de maig<br /> Horari: de 10 a 12:30h.<br /> Preu: 20 € (inclou tots els materials)<br /> INSCRIPCIÓ PRÈVIA / Màxim 10 alumnes. <br /> <br /> Aprendrem a insolar i crear segells a partir d'una imatge impresa. Una tècnica molt econòmica i fàcil de reproduir a casa! Estamparem sobre tèxtil i paper creant composicions amb dissenys de sòls hidràulics de Barcelona! <br /> Un curs 100% Do It Yourself molt útil i divertit!<br /> <br /> http://www.dinamo-studio.com/agenda/taller-de-sellos/<br /> <br /> - - - - -  - -<br /> <br /> CHRISTIAN GARCÍA JOYERIA CONTEMPORÀNIA<br /> Exposició i venda al Local G<br /> <br /> HORARI<br /> Divendres i dissabte d'11 a 14h. i de 17 a 21h.<br /> Diumenge d'11 a 14h.<br /> <br /> www.christian-garcia.es<br /> <br /> - - - - -  - - Ver más</p>","EVENT IMAGE":"https://scontent-mad1-1.xx.fbcdn.net/v/t1.0-0/s526x296/31378788_2173031986057069_2986424592089743360_n.jpg?_nc_cat=0&_nc_eui2=v1%3AAeFcJfFObXgvl-l2ztd3Bp37izMjE8gGgRTQKbQ6H6I_e7JDifzvX24dziwZ_l8Y8CSRkYhAXFKkZDPBvoqr8_PJq4XLBgBMTu-HJfuaeTp7Og&oh=7c686b7ffc75f1a26c0694545492419b&oe=5B580288"},{"EVENT NAME":"Tallers Oberts Tria'm amb Zirt Zart","VENUE NAME":"null","ORGANIZER NAME":"Zirt Zart","START DATE":"05/11/2018","START TIME":"","END DATE":"05/13/2018","END TIME":"","ALL DAY EVENT?":1,"CATEGORIES":"","EVENT COST":"","EVENT WEBSITE":"https://www.facebook.com/events/170440700338751/","SHOW MAP LINK?":1,"SHOW MAP?":1,"EVENT DESCRIPTION":"<p><img src='http://scontent-mad1-1.xx.fbcdn.net/v/t1.0-0/p280x280/31914327_2019185341626542_6189801365418541056_n.jpg?_nc_cat=0&_nc_eui2=v1%3AAeHcZrpPCkL-FUcLP8vWVuoWFwZN6An1M1R0GLa9BBsb7DZCcIc2YISwIt6Bvn1ij1LjyHqB48ni0XwXRRnl37CiYnZZd6MWPRWRwQFUupBbgQ&oh=fc787942c7cfb2f76846bb0b40192685&oe=5B845C3A' width='228' height='182' alt='Tallers Oberts Tria'm amb Zirt Zart' />Vine a Coneixer-nos a les jornades de PORTES OBERTES!!<br /> <br /> - A C T I V I T A T - <br /> Tria les nostres robes de Zirt Zart i atreveix-te a fer la teva creació. <br /> Després, queda't al pica-pica.<br /> Taller gratüit per tots els publics.<br /> <br /> Diumenge, 13 de maig de 11 a 13 h.<br /> T'esperem!</p>","EVENT IMAGE":"https://scontent-mad1-1.xx.fbcdn.net/v/t1.0-0/p280x280/31914327_2019185341626542_6189801365418541056_n.jpg?_nc_cat=0&_nc_eui2=v1%3AAeHcZrpPCkL-FUcLP8vWVuoWFwZN6An1M1R0GLa9BBsb7DZCcIc2YISwIt6Bvn1ij1LjyHqB48ni0XwXRRnl37CiYnZZd6MWPRWRwQFUupBbgQ&oh=fc787942c7cfb2f76846bb0b40192685&oe=5B845C3A"}]
