[
  {
    "event_link": "Más >",
    "event_link-href": "http://www.museudeldisseny.cat/es/exposicion/distincion-un-siglo-de-fotografia-de-moda",
    "event_title": "Distinción. Un siglo de fotografía de moda",
    "event_image-src": "http://www.museudeldisseny.cat/sites/default/files/styles/16_9_half/public/exhibition/mtib_3.885_13_0.jpg?itok=CXHvh_km",
    "event_text": "La exposición tiene como punto de partida la colección de fotografía de moda del Museu del Disseny de Barcelona que comprende 35 autores con un total de 464 fotografías de diferentes dimensiones, de entre 1903 y 2013.",
    "event_start": "25 / 11 / 2015",
    "event_end": "27 / 03 / 2016",
    "event_maplink__1": "null",
    "event_cost__5": "null",
    "event_organizer__Museu del Disseny": "null",
    "event_venue__Museu del Disseny": "null",
    "event_category__Museu del Disseny__Diseño": "null",
    "event_id": "Distinción. Un siglo de fotografía de moda \n    \n            Temporal\n                  \n\t\t25 / 11 / 2015\n\t\t\t - \n\t27 / 03 / 2016"
  }
]